{"textures":[{"image":"vippenthouse-0.webp","format":"RGBA8888","size":{"w":1522,"h":1924},"scale":1,"frames":[{"filename":"bg","rotated":false,"trimmed":false,"sourceSize":{"w":1520,"h":960},"spriteSourceSize":{"x":0,"y":0,"w":1520,"h":960},"frame":{"x":1,"y":1,"w":1520,"h":960}},{"filename":"fg","rotated":false,"trimmed":true,"sourceSize":{"w":1520,"h":960},"spriteSourceSize":{"x":885,"y":0,"w":612,"h":960},"frame":{"x":1,"y":963,"w":612,"h":960}}]}],"meta":{"app":"https://www.codeandweb.com/texturepacker","version":"3.0","smartupdate":"$TexturePacker:SmartUpdate:2f277ad8e4c327811ef9390522fd5486:99a30ee1f4a7423d63a7e3033bd33821:b44244740fe9ad5ed306b69650a00392$"}}