{"textures":[{"image":"springpalace-0.webp","format":"RGBA8888","size":{"w":1514,"h":1188},"scale":1,"frames":[{"filename":"fg","rotated":false,"trimmed":true,"sourceSize":{"w":1520,"h":960},"spriteSourceSize":{"x":944,"y":582,"w":566,"h":263},"frame":{"x":1,"y":1,"w":566,"h":263}},{"filename":"door","rotated":false,"trimmed":true,"sourceSize":{"w":112,"h":317},"spriteSourceSize":{"x":0,"y":12,"w":43,"h":286},"frame":{"x":569,"y":1,"w":43,"h":286}},{"filename":"door-hover","rotated":false,"trimmed":false,"sourceSize":{"w":112,"h":317},"spriteSourceSize":{"x":0,"y":0,"w":112,"h":317},"frame":{"x":614,"y":1,"w":112,"h":317}},{"filename":"bg","rotated":false,"trimmed":true,"sourceSize":{"w":1520,"h":960},"spriteSourceSize":{"x":8,"y":0,"w":1512,"h":867},"frame":{"x":1,"y":320,"w":1512,"h":867}}]}],"meta":{"app":"https://www.codeandweb.com/texturepacker","version":"3.0","smartupdate":"$TexturePacker:SmartUpdate:187280323b0a4c00ab26ac24827da9ea:65455e5c463092f22d13c50a469a26d5:99df04e63cab94facd601830ba634970$"}}